idf/Hdf5File.py
idf/__init__.py
idf/genFortran.py
idf/genJava.py
idf/idf.py
idf-0.0.1.dist-info/LICENSE
idf-0.0.1.dist-info/METADATA
idf-0.0.1.dist-info/WHEEL
idf-0.0.1.dist-info/top_level.txt
idf-0.0.1.dist-info/RECORD
